sslcalculator/__init__.py
sslcalculator-0.1.dist-info/Licence.txt
sslcalculator-0.1.dist-info/METADATA
sslcalculator-0.1.dist-info/WHEEL
sslcalculator-0.1.dist-info/top_level.txt
sslcalculator-0.1.dist-info/RECORD
