Metadata-Version: 2.1
Name: sslcalculator
Version: 0.1
Summary: basic calculator
Author: srisailam
Author-email: kakuralasrisailam@gmail.com
Classifier: Programming Language :: Python :: 3
Classifier: License :: OSI Approved :: MIT License
Classifier: Operating System :: OS Independent
License-File: Licence.txt
